fontmeta.py
fontmeta-1.0.0.dist-info/DESCRIPTION.rst
fontmeta-1.0.0.dist-info/METADATA
fontmeta-1.0.0.dist-info/RECORD
fontmeta-1.0.0.dist-info/WHEEL
fontmeta-1.0.0.dist-info/entry_points.txt
fontmeta-1.0.0.dist-info/metadata.json
fontmeta-1.0.0.dist-info/top_level.txt
