Metadata-Version: 2.0
Name: fontmeta
Version: 1.0.0
Summary: An Utility to get ttf/otf font metadata
Home-page: https://github.com/codesigntheory/fontmeta
Author: Utsob Roy
Author-email: roy@codesign.com.bd
License: MIT
Keywords: Font TTF OTF
Platform: UNKNOWN
Classifier: Development Status :: 5 - Production/Stable
Classifier: Intended Audience :: Developers
Classifier: Topic :: Software Development :: Libraries :: Python Modules
Classifier: License :: OSI Approved :: MIT License
Classifier: Programming Language :: Python :: 3 :: Only
Requires-Dist: fonttools
